{"cameraMode":{"drawMode":0,"name":"Shaded","section":"Shading Mode"},"sceneLighting":false,"audioPlay":false,"sceneViewState":{"m_AlwaysRefresh":false,"showFog":true,"showSkybox":false,"showFlares":true,"showImageEffects":true,"showParticleSystems":true,"showVisualEffectGraphs":true,"m_FxEnabled":true},"in2DMode":false,"pivot":{"x":0.02795886993408203,"y":4.819133281707764,"z":0.28096961975097659},"rotation":{"x":-0.4365781843662262,"y":-0.012991893105208874,"z":0.0062198331579566,"w":-0.8996251225471497},"size":14.371859550476075,"orthographic":false}